django_fast_utils/__init__.py
django_fast_utils/apps.py
django_fast_utils/backends.py
django_fast_utils/exceptions.py
django_fast_utils/fields.py
django_fast_utils/helpers.py
django_fast_utils/paginator.py
django_fast_utils/permissions.py
django_fast_utils/settings.py
django_fast_utils/auth/__init__.py
django_fast_utils/auth/backends.py
django_fast_utils/auth/generics.py
django_fast_utils/auth/middleware.py
django_fast_utils/db/__init__.py
django_fast_utils/db/fields.py
django_fast_utils/utils/__init__.py
django_fast_utils/utils/audit.py
django_fast_utils/views/__init__.py
django_fast_utils/views/generics.py
django_fast_utils/views/auth/__init__.py
django_fast_utils/views/auth/serializers.py
django_fast_utils/views/auth/views.py
django_fast_utils-2.0.4.dist-info/AUTHORS
django_fast_utils-2.0.4.dist-info/LICENSE
django_fast_utils-2.0.4.dist-info/METADATA
django_fast_utils-2.0.4.dist-info/WHEEL
django_fast_utils-2.0.4.dist-info/top_level.txt
django_fast_utils-2.0.4.dist-info/RECORD
