Metadata-Version: 2.1
Name: django-fast-utils
Version: 2.0.4
Summary: Utils for Django with little effort.
Home-page: https://tarsil.github.io/django-fast-utils/
Author: Tiago Silva
Author-email: tiago.arasilva@gmail.com
License: MIT
Platform: UNKNOWN
Classifier: Development Status :: 5 - Production/Stable
Classifier: Environment :: Web Environment
Classifier: Framework :: Django
Classifier: Framework :: Django :: 2.2
Classifier: Framework :: Django :: 3.0
Classifier: Framework :: Django :: 3.1
Classifier: Framework :: Django :: 3.2
Classifier: Framework :: Django :: 4.0
Classifier: Intended Audience :: Developers
Classifier: License :: OSI Approved :: BSD License
Classifier: Operating System :: OS Independent
Classifier: Programming Language :: Python
Classifier: Programming Language :: Python :: 3
Classifier: Programming Language :: Python :: 3.6
Classifier: Programming Language :: Python :: 3.7
Classifier: Programming Language :: Python :: 3.8
Classifier: Programming Language :: Python :: 3.9
Classifier: Programming Language :: Python :: 3.10
Classifier: Programming Language :: Python :: 3 :: Only
Classifier: Topic :: Internet :: WWW/HTTP
Requires-Python: >=3.7
License-File: LICENSE
License-File: AUTHORS
Requires-Dist: django (>=2.2)
Requires-Dist: pytz
Requires-Dist: django-guardian (>=2.4.0)
Requires-Dist: djangorestframework-simplejwt (>=5.2.0)
